weby_pilot/__init__.py
weby_pilot/__main__.py
weby_pilot/base.py
weby_pilot/big.py
weby_pilot/bpi.py
weby_pilot/common.py
weby_pilot/errors.py
weby_pilot-0.1.9.dist-info/METADATA
weby_pilot-0.1.9.dist-info/WHEEL
weby_pilot-0.1.9.dist-info/top_level.txt
weby_pilot-0.1.9.dist-info/RECORD
